README.md
setup.cfg
setup.py
randomuser/__init__.py
randomuser/randomuser.py
randomuser/version.py
randomuser.egg-info/PKG-INFO
randomuser.egg-info/SOURCES.txt
randomuser.egg-info/dependency_links.txt
randomuser.egg-info/not-zip-safe
randomuser.egg-info/top_level.txt