Metadata-Version: 1.1
Name: randomuser
Version: 1.1.0
Summary: Python class for generating random user data using https://randomuser.me API
Home-page: http://connordelacruz.com/python-randomuser/
Author: Connor de la Cruz
Author-email: connor.c.delacruz@gmail.com
License: MIT
Download-URL: https://github.com/connordelacruz/python-randomuser/archive/1.1.0.tar.gz
Platform: UNKNOWN
